cgbeacon2/__init__.py
cgbeacon2/__version__.py
cgbeacon2/cli/__init__.py
cgbeacon2/cli/add.py
cgbeacon2/cli/commands.py
cgbeacon2/cli/delete.py
cgbeacon2/cli/update.py
cgbeacon2/constants/__init__.py
cgbeacon2/constants/oauth_errors.py
cgbeacon2/constants/query_errors.py
cgbeacon2/constants/request_errors.py
cgbeacon2/constants/response_objs.py
cgbeacon2/constants/variant_constants.py
cgbeacon2/instance/__init__.py
cgbeacon2/instance/config.py
cgbeacon2/models/__init__.py
cgbeacon2/models/beacon.py
cgbeacon2/models/dataset_response.py
cgbeacon2/models/user.py
cgbeacon2/models/variant.py
cgbeacon2/resources/__init__.py
cgbeacon2/resources/demo/__init__.py
cgbeacon2/server/__init__.py
cgbeacon2/server/auto.py
cgbeacon2/server/blueprints/__init__.py
cgbeacon2/server/blueprints/api_v1/__init__.py
cgbeacon2/server/blueprints/api_v1/controllers.py
cgbeacon2/server/blueprints/api_v1/views.py
cgbeacon2/utils/__init__.py
cgbeacon2/utils/add.py
cgbeacon2/utils/auth.py
cgbeacon2/utils/delete.py
cgbeacon2/utils/ensembl_biomart.py
cgbeacon2/utils/md5.py
cgbeacon2/utils/notify.py
cgbeacon2/utils/parse.py
cgbeacon2/utils/update.py
tests/__init__.py
tests/conftest.py
cgbeacon2-4.5.1.dist-info/LICENSE
cgbeacon2-4.5.1.dist-info/METADATA
cgbeacon2-4.5.1.dist-info/WHEEL
cgbeacon2-4.5.1.dist-info/entry_points.txt
cgbeacon2-4.5.1.dist-info/top_level.txt
cgbeacon2-4.5.1.dist-info/RECORD
