Metadata-Version: 2.1
Name: cgbeacon2
Version: 4.5.1
Summary: A beacon supporting GA4GH API 1.0
Home-page: https://github.com/Clinical-Genomics/cgbeacon2
Author: Chiara Rasi
Author-email: chiara.rasi@scilifelab.se
License: MIT
Download-URL: https://github.com/Clinical-Genomics/cgbeacon2/tarball/4.5.1
Keywords: rare diseases,genomics,variants,beacon,genetic disease
Platform: UNKNOWN
Classifier: License :: OSI Approved :: MIT License
Classifier: Programming Language :: Python :: 3
Classifier: Programming Language :: Python :: 3.6
Classifier: Programming Language :: Python :: 3.7
Classifier: Programming Language :: Python :: 3.8
Classifier: Intended Audience :: Science/Research
Classifier: Operating System :: MacOS
Classifier: Operating System :: Unix
Requires-Dist: pymongo
Requires-Dist: click
Requires-Dist: progress
Requires-Dist: flask
Requires-Dist: flask-executor
Requires-Dist: requests
Requires-Dist: flask-negotiate
Requires-Dist: werkzeug
Requires-Dist: authlib
Requires-Dist: PyJWT >=2.0
Requires-Dist: uuid
Requires-Dist: cyvcf2
Requires-Dist: pybedtools
Requires-Dist: jsonschema
